invest_tools/__init__.py
invest_tools/analysis.py
invest_tools/currency.py
invest_tools/log.py
invest_tools/plot.py
invest_tools/portfolio.py
invest_tools/validation.py
invest_tools-0.3.0.dist-info/LICENSE
invest_tools-0.3.0.dist-info/WHEEL
invest_tools-0.3.0.dist-info/METADATA
invest_tools-0.3.0.dist-info/RECORD
